[
  {
    "isCombination": false,
    "minPromotionOrderPrice": 0,
    "productVideoId": 0,
    "originOrderCount": 0,
    "productBrand": {
      "modifyTime": null,
      "dbid": 2548203,
      "name": "润百颜",
      "id": 7561182,
      "status": 0
    },
    "mulspec3Value": "",
    "minPromotionOrderRate": 0,
    "promotionStatus": "",
    "property2": "",
    "property1": "",
    "property4": "",
    "property3": "",
    "queryProductTypeIds": [],
    "queryStatus": [],
    "valueSpecDesc": "",
    "inventories": [],
    "inventoryModifyTime": {
      "date": 23,
      "hours": 17,
      "seconds": 41,
      "month": 11,
      "timezoneOffset": -480,
      "year": 125,
      "minutes": 1,
      "time": 1766480501000,
      "day": 2
    },
    "productVideoModel": null,
    "beginTime": "",
    "id": 1028123685,
    "mulspecList": null,
    "mainUnitId": 0,
    "mulspec3Name": "",
    "costPriceSql": 0,
    "specDesc": "",
    "mainPrice": 0,
    "inventoryStatus": "",
    "queryProductInventoryStatus": [],
    "productBrandId": 7561182,
    "showTypeIds": [],
    "version": 0,
    "packagespecStatus": "0",
    "isScekillProduct": "",
    "mainUnitName": "",
    "outModifyTime": "",
    "isForbidden": "",
    "imgUrl_60": "2548203/b8ba70fb-e056-481c-963e-3b62f06a5a89.png@0-0-1000-1000a_60w_60h.png",
    "mulspec1Value": "",
    "mulspec4Value": "",
    "dbid": 2548203,
    "inventoryVersion": 6,
    "onWayCount": 0,
    "mulspec1Name": "",
    "status": "0",
    "marketPrice": 9660,
    "productSummaryId": 1028123686,
    "inventoryUpWarn": -1,
    "modifyEndTime": "",
    "packageSpec3Value": "",
    "orderPriceSql": 9660,
    "marketPriceSql": 9660,
    "shoppingCart": {},
    "queryProductIds": [],
    "sortNum": 9,
    "existImage": false,
    "productCombinationContents": [],
    "productSpec": "",
    "syncProduct": false,
    "costPrice": 0,
    "inventoryCount": 1,
    "mulspecTemplateName": "",
    "imgUrl_200": "2548203/b8ba70fb-e056-481c-963e-3b62f06a5a89.png@0-0-1000-1000a_200w_200h.png",
    "multipleProductTypeModel": null,
    "exactBarcode": "",
    "promotionProductIds": [],
    "packageSpec2Name": "",
    "createTime": {
      "date": 26,
      "hours": 14,
      "seconds": 30,
      "month": 10,
      "timezoneOffset": -480,
      "year": 125,
      "minutes": 1,
      "time": 1764136890000,
      "day": 3
    },
    "productUnitName": "箱",
    "purchaseScore": 0,
    "albumList": [
      {
        "productId": 1028123685,
        "productSummaryId": 1028123686,
        "imgUrl_480": "2548203/3cfba3bc-f110-4a37-b730-cee5d4bb7d65.jpg@480w_480h.jpg",
        "remark": "",
        "imgUrl_200": "2548203/3cfba3bc-f110-4a37-b730-cee5d4bb7d65.jpg@200w_200h.jpg",
        "type": 1,
        "imgName": "主图_2.jpg",
        "imgUrl": "3cfba3bc-f110-4a37-b730-cee5d4bb7d65.jpg",
        "advanceCutSize": "",
        "proposeFormat": ".jpg",
        "size": 136198,
        "createTime": {
          "date": 1,
          "hours": 9,
          "seconds": 35,
          "month": 11,
          "timezoneOffset": -480,
          "year": 125,
          "minutes": 39,
          "time": 1764553175000,
          "day": 1
        },
        "imgUrl_60": "2548203/3cfba3bc-f110-4a37-b730-cee5d4bb7d65.jpg@60w_60h.jpg",
        "dbid": 2548203,
        "sortNum": 0,
        "id": 135693677,
        "imgUrl_cut": "2548203/3cfba3bc-f110-4a37-b730-cee5d4bb7d65.jpg",
        "imgVersion": 1000
      },
      {
        "productId": 1028123685,
        "productSummaryId": 1028123686,
        "imgUrl_480": "2548203/7b9369a8-a38c-4cfe-8993-d7b81867ca10.jpg@480w_480h.jpg",
        "remark": "",
        "imgUrl_200": "2548203/7b9369a8-a38c-4cfe-8993-d7b81867ca10.jpg@200w_200h.jpg",
        "type": 1,
        "imgName": "主图_3.jpg",
        "imgUrl": "7b9369a8-a38c-4cfe-8993-d7b81867ca10.jpg",
        "advanceCutSize": "",
        "proposeFormat": ".jpg",
        "size": 102760,
        "createTime": {
          "date": 1,
          "hours": 9,
          "seconds": 35,
          "month": 11,
          "timezoneOffset": -480,
          "year": 125,
          "minutes": 39,
          "time": 1764553175000,
          "day": 1
        },
        "imgUrl_60": "2548203/7b9369a8-a38c-4cfe-8993-d7b81867ca10.jpg@60w_60h.jpg",
        "dbid": 2548203,
        "sortNum": 1,
        "id": 135693678,
        "imgUrl_cut": "2548203/7b9369a8-a38c-4cfe-8993-d7b81867ca10.jpg",
        "imgVersion": 1000
      },
      {
        "productId": 1028123685,
        "productSummaryId": 1028123686,
        "imgUrl_480": "2548203/d5eb5608-bf21-4a75-9aec-9bcb7a6a6bb3.jpg@480w_480h.jpg",
        "remark": "",
        "imgUrl_200": "2548203/d5eb5608-bf21-4a75-9aec-9bcb7a6a6bb3.jpg@200w_200h.jpg",
        "type": 1,
        "imgName": "主图_4.jpg",
        "imgUrl": "d5eb5608-bf21-4a75-9aec-9bcb7a6a6bb3.jpg",
        "advanceCutSize": "",
        "proposeFormat": ".jpg",
        "size": 107045,
        "createTime": {
          "date": 1,
          "hours": 9,
          "seconds": 35,
          "month": 11,
          "timezoneOffset": -480,
          "year": 125,
          "minutes": 39,
          "time": 1764553175000,
          "day": 1
        },
        "imgUrl_60": "2548203/d5eb5608-bf21-4a75-9aec-9bcb7a6a6bb3.jpg@60w_60h.jpg",
        "dbid": 2548203,
        "sortNum": 2,
        "id": 135693679,
        "imgUrl_cut": "2548203/d5eb5608-bf21-4a75-9aec-9bcb7a6a6bb3.jpg",
        "imgVersion": 1000
      },
      {
        "productId": 1028123685,
        "productSummaryId": 1028123686,
        "imgUrl_480": "2548203/1f20a64c-74e0-4704-a275-a363d0569fb4.jpg@480w_480h.jpg",
        "remark": "",
        "imgUrl_200": "2548203/1f20a64c-74e0-4704-a275-a363d0569fb4.jpg@200w_200h.jpg",
        "type": 1,
        "imgName": "主图_5.jpg",
        "imgUrl": "1f20a64c-74e0-4704-a275-a363d0569fb4.jpg",
        "advanceCutSize": "",
        "proposeFormat": ".jpg",
        "size": 79116,
        "createTime": {
          "date": 1,
          "hours": 9,
          "seconds": 35,
          "month": 11,
          "timezoneOffset": -480,
          "year": 125,
          "minutes": 39,
          "time": 1764553175000,
          "day": 1
        },
        "imgUrl_60": "2548203/1f20a64c-74e0-4704-a275-a363d0569fb4.jpg@60w_60h.jpg",
        "dbid": 2548203,
        "sortNum": 3,
        "id": 135693680,
        "imgUrl_cut": "2548203/1f20a64c-74e0-4704-a275-a363d0569fb4.jpg",
        "imgVersion": 1000
      }
    ],
    "property10": "",
    "mulspec5Name": "",
    "endTime": "",
    "mulspecTemplateId": 0,
    "comboFlag": false,
    "keywords": "",
    "packageSpec1Value": "",
    "sortTime": {
      "date": 1,
      "hours": 9,
      "seconds": 35,
      "month": 11,
      "timezoneOffset": -480,
      "year": 125,
      "minutes": 39,
      "time": 1764553175000,
      "day": 1
    },
    "modifyBeginTime": "",
    "promotionStrategyList": [],
    "spec": "",
    "modifyTime": {
      "date": 23,
      "hours": 17,
      "seconds": 41,
      "month": 11,
      "timezoneOffset": -480,
      "year": 125,
      "minutes": 1,
      "time": 1766480501000,
      "day": 2
    },
    "packageSpec2Value": "",
    "shoppingCartProductType": 0,
    "productTypeName": "",
    "queryProductBrandIds": [],
    "warningCount": -1,
    "surplusCostMoney": 0,
    "barcode": "",
    "productCollection": {},
    "priceCustomerList": [],
    "weight": 0,
    "mainCount": 0,
    "promotionStrategy": {},
    "mulspec2Name": "",
    "inventoryCountisForbid": 0,
    "name": "^【箱规】润百颜水光嘭弹次抛精华液1.3ml*5支/袋*140袋/箱",
    "desimgList": [],
    "isGroup": "0",
    "productOrderMultiple": 0,
    "dataSource": "",
    "queryBarcode": "",
    "packageSpec1Name": "",
    "mainImg": {
      "productId": 1028123685,
      "productSummaryId": 1028123686,
      "imgUrl_480": "2548203/b8ba70fb-e056-481c-963e-3b62f06a5a89.png@0-0-1000-1000a_480w_480h.png",
      "remark": "",
      "imgUrl_200": "2548203/b8ba70fb-e056-481c-963e-3b62f06a5a89.png@0-0-1000-1000a_200w_200h.png",
      "type": 0,
      "imgName": "主.png",
      "imgUrl": "b8ba70fb-e056-481c-963e-3b62f06a5a89.png",
      "advanceCutSize": "0-0-1000-1000",
      "proposeFormat": ".png",
      "size": 620415,
      "createTime": {
        "date": 1,
        "hours": 9,
        "seconds": 35,
        "month": 11,
        "timezoneOffset": -480,
        "year": 125,
        "minutes": 39,
        "time": 1764553175000,
        "day": 1
      },
      "imgUrl_60": "2548203/b8ba70fb-e056-481c-963e-3b62f06a5a89.png@0-0-1000-1000a_60w_60h.png",
      "dbid": 2548203,
      "sortNum": 0,
      "id": 135693676,
      "imgUrl_cut": "2548203/b8ba70fb-e056-481c-963e-3b62f06a5a89.png@0-0-1000-1000a.png",
      "imgVersion": 1000
    },
    "code": "P2025112602",
    "supplierId": 0,
    "priceListCustomer": [],
    "productSummaryIds": [],
    "customAttributeStitch": "",
    "tagIds": [
      1,
      2405337,
      2408315,
      2408318,
      2409520
    ],
    "unitList": [
      {
        "marketPrice": 9660,
        "unitName": "箱",
        "forbidden": "0",
        "productSummaryId": 1028123686,
        "costPrice": 0,
        "version": 0,
        "returnOrderPrice": 0,
        "modifyTime": null,
        "createTime": null,
        "rate": 1,
        "dbid": 0,
        "unitId": 8811866,
        "orderPrice": 9660,
        "id": 0,
        "barcode": ""
      }
    ],
    "description": "&#60;p&#62;商品介绍&#60;/p&#62;&#60;p&#62;&#60;img src=&#34;https://oss.dinghuo123.com/product/detail/images/2548203/a4b9aaf7-4015-4ec6-99f4-342a9cc8ca8d.jpg&#34;/&#62;&#60;img src=&#34;https://oss.dinghuo123.com/product/detail/images/2548203/6eb41406-bebd-4cd9-a844-ea29837f6575.jpg&#34;/&#62;&#60;img src=&#34;https://oss.dinghuo123.com/product/detail/images/2548203/5de2a475-03ff-4fee-aa45-9fa9010c1b84.jpg&#34;/&#62;&#60;img src=&#34;https://oss.dinghuo123.com/product/detail/images/2548203/659814a3-5c05-4a99-9a57-0a489988d198.jpg&#34;/&#62;&#60;img src=&#34;https://oss.dinghuo123.com/product/detail/images/2548203/1cea5832-a653-4c23-901d-5c80b00eda92.jpg&#34;/&#62;&#60;img src=&#34;https://oss.dinghuo123.com/product/detail/images/2548203/8b5fa267-01fc-4be1-b677-4919b59b1d56.jpg&#34;/&#62;&#60;img src=&#34;https://oss.dinghuo123.com/product/detail/images/2548203/3a82c0d1-cc15-4a75-bd01-c7f19477ba1d.jpg&#34;/&#62;&#60;img src=&#34;https://oss.dinghuo123.com/product/detail/images/2548203/817f2bed-ffd5-4622-aa2d-3b68ce3599d0.jpg&#34;/&#62;&#60;img src=&#34;https://oss.dinghuo123.com/product/detail/images/2548203/f5ee7a66-845e-4cd1-8c41-d14fd022b4a8.jpg&#34;/&#62;&#60;img src=&#34;https://oss.dinghuo123.com/product/detail/images/2548203/c031c953-eb25-4cf9-9e5c-f8294d11283f.jpg&#34;/&#62;&#60;img src=&#34;https://oss.dinghuo123.com/product/detail/images/2548203/7477db18-81b5-4de4-961e-21c37478c3e7.jpg&#34;/&#62;&#60;img src=&#34;https://oss.dinghuo123.com/product/detail/images/2548203/259bee47-f3ac-4f9e-b469-472de3f988d4.jpg&#34;/&#62;&#60;img src=&#34;https://oss.dinghuo123.com/product/detail/images/2548203/02252e39-5ef6-4512-a106-4abe07e18a0d.jpg&#34;/&#62;&#60;img src=&#34;https://oss.dinghuo123.com/product/detail/images/2548203/41a57c0b-b730-4ab9-81c8-edd09756aa1d.jpg&#34;/&#62;&#60;img src=&#34;https://oss.dinghuo123.com/product/detail/images/2548203/db6751de-8eac-466d-9f5b-a7f30651e4a2.jpg&#34;/&#62;&#60;/p&#62;",
    "queryInventoryStatus": [],
    "remark": "",
    "isCart": false,
    "delete": "0",
    "priceList": [
      {
        "marketPrice": 0,
        "product": null,
        "productId": 1028123685,
        "maxQuantity": 0,
        "productSummaryId": 1028123686,
        "remark": "",
        "unitPrices": [
          {
            "unitId": 8811866,
            "orderPrice": 2170
          }
        ],
        "customerTypeId": 4331189,
        "customerType": null,
        "modifyTime": {
          "date": 1,
          "hours": 9,
          "seconds": 35,
          "month": 11,
          "timezoneOffset": -480,
          "year": 125,
          "minutes": 39,
          "time": 1764553175000,
          "day": 1
        },
        "isForbidden": "0",
        "minQuantity": 0,
        "unitListPrice": [],
        "dbid": 2548203,
        "orderPrice": 2170,
        "id": 8549140861,
        "status": ""
      }
    ],
    "productUnitId": 8811866,
    "subProductList": [],
    "priceListType": [
      {
        "marketPrice": 0,
        "product": null,
        "productId": 1028123685,
        "maxQuantity": 0,
        "productSummaryId": 1028123686,
        "remark": "",
        "unitPrices": [
          {
            "unitId": 8811866,
            "orderPrice": 2170
          }
        ],
        "customerTypeId": 4331189,
        "customerType": null,
        "modifyTime": {
          "date": 1,
          "hours": 9,
          "seconds": 35,
          "month": 11,
          "timezoneOffset": -480,
          "year": 125,
          "minutes": 39,
          "time": 1764553175000,
          "day": 1
        },
        "isForbidden": "0",
        "minQuantity": 0,
        "unitListPrice": [],
        "dbid": 2548203,
        "orderPrice": 2170,
        "id": 8549140861,
        "status": ""
      }
    ],
    "customerTypeId": 0,
    "attachmentList": [],
    "productAuxUnit": null,
    "c_extra": {},
    "prepareCount": 0,
    "orderPrice": 9660,
    "imgUrl_cut": "2548203/b8ba70fb-e056-481c-963e-3b62f06a5a89.png@0-0-1000-1000a.png",
    "returnCart": null,
    "productType": {
      "mainImg": null,
      "parentTypeId": 0,
      "src": "",
      "typeLevel": 1,
      "imgUrl_200": "",
      "leafTypeFlag": "1",
      "subTypeTotalNum": 0,
      "advanceCutSize": "",
      "isDefault": "",
      "modifyTime": null,
      "showPageType": 1,
      "dbid": 2548203,
      "mainImgUrl": "",
      "name": "重点品-Q",
      "id": 25561309,
      "subTypeList": [],
      "status": "0"
    },
    "productTagModelList": [],
    "mulspec2Value": "",
    "pullNewCommissionRuleVO": null,
    "mulspec5Value": "",
    "album": [
      "2548203/3cfba3bc-f110-4a37-b730-cee5d4bb7d65.jpg",
      "2548203/7b9369a8-a38c-4cfe-8993-d7b81867ca10.jpg",
      "2548203/d5eb5608-bf21-4a75-9aec-9bcb7a6a6bb3.jpg",
      "2548203/1f20a64c-74e0-4704-a275-a363d0569fb4.jpg"
    ],
    "multiUnitTemp": "",
    "tagIdsLike": [],
    "property9": "",
    "imgUrl_480": "2548203/b8ba70fb-e056-481c-963e-3b62f06a5a89.png@0-0-1000-1000a_480w_480h.png",
    "packageSpec3Name": "",
    "property6": "",
    "mulspec4Name": "",
    "property5": "",
    "productTypeId": 25561309,
    "property8": "",
    "property7": "",
    "imgUrl": "2548203/b8ba70fb-e056-481c-963e-3b62f06a5a89.png@0-0-1000-1000a.png",
    "salesProducts": [],
    "opTime": {
      "date": 29,
      "hours": 20,
      "seconds": 26,
      "month": 10,
      "timezoneOffset": -480,
      "year": 125,
      "minutes": 26,
      "time": 1764419186000,
      "day": 6
    },
    "summaryCount": 0
  }
]