[
  {
    "isCombination": false,
    "minPromotionOrderPrice": 0,
    "productVideoId": 0,
    "originOrderCount": 0,
    "productBrand": {
      "modifyTime": null,
      "dbid": 2548203,
      "name": "益肤",
      "id": 12781381,
      "status": 0
    },
    "mulspec3Value": "",
    "minPromotionOrderRate": 0,
    "promotionStatus": "",
    "property2": "",
    "property1": "",
    "property4": "",
    "property3": "",
    "queryProductTypeIds": [],
    "queryStatus": [],
    "valueSpecDesc": "",
    "inventories": [],
    "inventoryModifyTime": {
      "date": 4,
      "hours": 16,
      "seconds": 25,
      "month": 0,
      "timezoneOffset": -480,
      "year": 126,
      "minutes": 9,
      "time": 1767514165000,
      "day": 0
    },
    "productVideoModel": null,
    "beginTime": "",
    "id": 717012097,
    "mulspecList": null,
    "mainUnitId": 0,
    "mulspec3Name": "",
    "costPriceSql": 0,
    "specDesc": "",
    "mainPrice": 0,
    "inventoryStatus": "",
    "queryProductInventoryStatus": [],
    "productBrandId": 12781381,
    "showTypeIds": [],
    "version": 0,
    "packagespecStatus": "0",
    "isScekillProduct": "",
    "mainUnitName": "",
    "outModifyTime": "",
    "isForbidden": "",
    "imgUrl_60": "2548203/215733a4-cadf-4e8f-be1a-64225e374939.jpg@0-0-1280-1280a_60w_60h.jpg",
    "mulspec1Value": "",
    "mulspec4Value": "",
    "dbid": 2548203,
    "inventoryVersion": 1347,
    "onWayCount": 0,
    "mulspec1Name": "",
    "status": "0",
    "marketPrice": 208,
    "productSummaryId": 717012096,
    "inventoryUpWarn": -1,
    "modifyEndTime": "",
    "packageSpec3Value": "",
    "orderPriceSql": 208,
    "marketPriceSql": 208,
    "shoppingCart": {},
    "queryProductIds": [],
    "sortNum": 10,
    "existImage": false,
    "productCombinationContents": [],
    "productSpec": "",
    "syncProduct": false,
    "costPrice": 0,
    "inventoryCount": 113,
    "mulspecTemplateName": "",
    "imgUrl_200": "2548203/215733a4-cadf-4e8f-be1a-64225e374939.jpg@0-0-1280-1280a_200w_200h.jpg",
    "multipleProductTypeModel": null,
    "exactBarcode": "",
    "promotionProductIds": [],
    "packageSpec2Name": "",
    "createTime": {
      "date": 21,
      "hours": 10,
      "seconds": 19,
      "month": 5,
      "timezoneOffset": -480,
      "year": 122,
      "minutes": 41,
      "time": 1655779279000,
      "day": 2
    },
    "productUnitName": "瓶",
    "purchaseScore": 0,
    "albumList": [
      {
        "productId": 717012097,
        "productSummaryId": 717012096,
        "imgUrl_480": "2548203/65db3fcf-c1a5-41cc-93c4-29356feaddc4.png@480w_480h.png",
        "remark": "",
        "imgUrl_200": "2548203/65db3fcf-c1a5-41cc-93c4-29356feaddc4.png@200w_200h.png",
        "type": 1,
        "imgName": "头2.png",
        "imgUrl": "65db3fcf-c1a5-41cc-93c4-29356feaddc4.png",
        "advanceCutSize": "",
        "proposeFormat": ".png",
        "size": 338243,
        "createTime": {
          "date": 10,
          "hours": 15,
          "seconds": 46,
          "month": 11,
          "timezoneOffset": -480,
          "year": 125,
          "minutes": 15,
          "time": 1765350946000,
          "day": 3
        },
        "imgUrl_60": "2548203/65db3fcf-c1a5-41cc-93c4-29356feaddc4.png@60w_60h.png",
        "dbid": 2548203,
        "sortNum": 0,
        "id": 135846355,
        "imgUrl_cut": "2548203/65db3fcf-c1a5-41cc-93c4-29356feaddc4.png",
        "imgVersion": 1000
      },
      {
        "productId": 717012097,
        "productSummaryId": 717012096,
        "imgUrl_480": "2548203/f59a9983-2d40-49b8-adb2-b18fdd1393e3.png@480w_480h.png",
        "remark": "",
        "imgUrl_200": "2548203/f59a9983-2d40-49b8-adb2-b18fdd1393e3.png@200w_200h.png",
        "type": 1,
        "imgName": "头3.png",
        "imgUrl": "f59a9983-2d40-49b8-adb2-b18fdd1393e3.png",
        "advanceCutSize": "",
        "proposeFormat": ".png",
        "size": 409485,
        "createTime": {
          "date": 10,
          "hours": 15,
          "seconds": 46,
          "month": 11,
          "timezoneOffset": -480,
          "year": 125,
          "minutes": 15,
          "time": 1765350946000,
          "day": 3
        },
        "imgUrl_60": "2548203/f59a9983-2d40-49b8-adb2-b18fdd1393e3.png@60w_60h.png",
        "dbid": 2548203,
        "sortNum": 1,
        "id": 135846356,
        "imgUrl_cut": "2548203/f59a9983-2d40-49b8-adb2-b18fdd1393e3.png",
        "imgVersion": 1000
      },
      {
        "productId": 717012097,
        "productSummaryId": 717012096,
        "imgUrl_480": "2548203/478173a6-2862-406c-bb63-0090f33e4cc4.jpg@480w_480h.jpg",
        "remark": "",
        "imgUrl_200": "2548203/478173a6-2862-406c-bb63-0090f33e4cc4.jpg@200w_200h.jpg",
        "type": 1,
        "imgName": "头4.jpg",
        "imgUrl": "478173a6-2862-406c-bb63-0090f33e4cc4.jpg",
        "advanceCutSize": "",
        "proposeFormat": ".jpg",
        "size": 264301,
        "createTime": {
          "date": 10,
          "hours": 15,
          "seconds": 46,
          "month": 11,
          "timezoneOffset": -480,
          "year": 125,
          "minutes": 15,
          "time": 1765350946000,
          "day": 3
        },
        "imgUrl_60": "2548203/478173a6-2862-406c-bb63-0090f33e4cc4.jpg@60w_60h.jpg",
        "dbid": 2548203,
        "sortNum": 2,
        "id": 135846357,
        "imgUrl_cut": "2548203/478173a6-2862-406c-bb63-0090f33e4cc4.jpg",
        "imgVersion": 1000
      },
      {
        "productId": 717012097,
        "productSummaryId": 717012096,
        "imgUrl_480": "2548203/907bb63d-c3d1-459d-a031-8522b62f8db7.jpg@480w_480h.jpg",
        "remark": "",
        "imgUrl_200": "2548203/907bb63d-c3d1-459d-a031-8522b62f8db7.jpg@200w_200h.jpg",
        "type": 1,
        "imgName": "头5.jpg",
        "imgUrl": "907bb63d-c3d1-459d-a031-8522b62f8db7.jpg",
        "advanceCutSize": "",
        "proposeFormat": ".jpg",
        "size": 270860,
        "createTime": {
          "date": 10,
          "hours": 15,
          "seconds": 46,
          "month": 11,
          "timezoneOffset": -480,
          "year": 125,
          "minutes": 15,
          "time": 1765350946000,
          "day": 3
        },
        "imgUrl_60": "2548203/907bb63d-c3d1-459d-a031-8522b62f8db7.jpg@60w_60h.jpg",
        "dbid": 2548203,
        "sortNum": 3,
        "id": 135846358,
        "imgUrl_cut": "2548203/907bb63d-c3d1-459d-a031-8522b62f8db7.jpg",
        "imgVersion": 1000
      },
      {
        "productId": 717012097,
        "productSummaryId": 717012096,
        "imgUrl_480": "2548203/c845f20a-0e79-4b9c-aeef-710acbe6492c.jpg@480w_480h.jpg",
        "remark": "",
        "imgUrl_200": "2548203/c845f20a-0e79-4b9c-aeef-710acbe6492c.jpg@200w_200h.jpg",
        "type": 1,
        "imgName": "头6.jpg",
        "imgUrl": "c845f20a-0e79-4b9c-aeef-710acbe6492c.jpg",
        "advanceCutSize": "",
        "proposeFormat": ".jpg",
        "size": 297747,
        "createTime": {
          "date": 10,
          "hours": 15,
          "seconds": 46,
          "month": 11,
          "timezoneOffset": -480,
          "year": 125,
          "minutes": 15,
          "time": 1765350946000,
          "day": 3
        },
        "imgUrl_60": "2548203/c845f20a-0e79-4b9c-aeef-710acbe6492c.jpg@60w_60h.jpg",
        "dbid": 2548203,
        "sortNum": 4,
        "id": 135846359,
        "imgUrl_cut": "2548203/c845f20a-0e79-4b9c-aeef-710acbe6492c.jpg",
        "imgVersion": 1000
      }
    ],
    "property10": "",
    "mulspec5Name": "",
    "endTime": "",
    "mulspecTemplateId": 0,
    "comboFlag": false,
    "keywords": "",
    "packageSpec1Value": "",
    "sortTime": {
      "date": 10,
      "hours": 15,
      "seconds": 46,
      "month": 11,
      "timezoneOffset": -480,
      "year": 125,
      "minutes": 15,
      "time": 1765350946000,
      "day": 3
    },
    "modifyBeginTime": "",
    "promotionStrategyList": [],
    "spec": "",
    "modifyTime": {
      "date": 4,
      "hours": 16,
      "seconds": 25,
      "month": 0,
      "timezoneOffset": -480,
      "year": 126,
      "minutes": 9,
      "time": 1767514165000,
      "day": 0
    },
    "packageSpec2Value": "",
    "shoppingCartProductType": 0,
    "productTypeName": "",
    "queryProductBrandIds": [],
    "warningCount": -1,
    "surplusCostMoney": 0,
    "barcode": "",
    "productCollection": {},
    "priceCustomerList": [],
    "weight": 0,
    "mainCount": 0,
    "promotionStrategy": {},
    "mulspec2Name": "",
    "inventoryCountisForbid": 0,
    "name": "益肤微分子玻尿酸屏障修护乳100ml/瓶",
    "desimgList": [],
    "isGroup": "0",
    "productOrderMultiple": 0,
    "dataSource": "",
    "queryBarcode": "",
    "packageSpec1Name": "",
    "mainImg": {
      "productId": 717012097,
      "productSummaryId": 717012096,
      "imgUrl_480": "2548203/215733a4-cadf-4e8f-be1a-64225e374939.jpg@0-0-1280-1280a_480w_480h.jpg",
      "remark": "",
      "imgUrl_200": "2548203/215733a4-cadf-4e8f-be1a-64225e374939.jpg@0-0-1280-1280a_200w_200h.jpg",
      "type": 0,
      "imgName": "头1.jpg",
      "imgUrl": "215733a4-cadf-4e8f-be1a-64225e374939.jpg",
      "advanceCutSize": "0-0-1280-1280",
      "proposeFormat": ".jpg",
      "size": 79990,
      "createTime": {
        "date": 10,
        "hours": 15,
        "seconds": 46,
        "month": 11,
        "timezoneOffset": -480,
        "year": 125,
        "minutes": 15,
        "time": 1765350946000,
        "day": 3
      },
      "imgUrl_60": "2548203/215733a4-cadf-4e8f-be1a-64225e374939.jpg@0-0-1280-1280a_60w_60h.jpg",
      "dbid": 2548203,
      "sortNum": 0,
      "id": 135846354,
      "imgUrl_cut": "2548203/215733a4-cadf-4e8f-be1a-64225e374939.jpg@0-0-1280-1280a.jpg",
      "imgVersion": 1000
    },
    "code": "P2022062104",
    "supplierId": 0,
    "priceListCustomer": [],
    "productSummaryIds": [],
    "customAttributeStitch": "",
    "tagIds": [
      1,
      5,
      2409520
    ],
    "unitList": [
      {
        "marketPrice": 208,
        "unitName": "瓶",
        "forbidden": "0",
        "productSummaryId": 717012096,
        "costPrice": 0,
        "version": 0,
        "returnOrderPrice": 0,
        "modifyTime": null,
        "createTime": null,
        "rate": 1,
        "dbid": 0,
        "unitId": 6872734,
        "orderPrice": 208,
        "id": 0,
        "barcode": ""
      }
    ],
    "description": "&#60;p&#62;商品介绍&#60;/p&#62;&#60;p&#62;&#60;img src=&#34;https://oss.dinghuo123.com/product/detail/images/2548203/77e0182c-ac83-4129-b518-172a2569fa4e.jpg&#34;/&#62;&#60;img src=&#34;https://oss.dinghuo123.com/product/detail/images/2548203/e198ae43-2c4f-4525-a3f0-8ca93e63fd56.jpg&#34;/&#62;&#60;img src=&#34;https://oss.dinghuo123.com/product/detail/images/2548203/876688b1-9ebc-4244-b5ad-de3bda44a0af.jpg&#34;/&#62;&#60;img src=&#34;https://oss.dinghuo123.com/product/detail/images/2548203/681112f1-822a-4c22-b2f6-95e4c722de1a.jpg&#34;/&#62;&#60;img src=&#34;https://oss.dinghuo123.com/product/detail/images/2548203/acdd9224-dcf8-4534-a796-ec81355ae1a7.jpg&#34;/&#62;&#60;img src=&#34;https://oss.dinghuo123.com/product/detail/images/2548203/5c8e9bba-b7fc-4664-9a7f-3db625fce5b0.jpg&#34;/&#62;&#60;img src=&#34;https://oss.dinghuo123.com/product/detail/images/2548203/64d8664c-b867-4ccb-84ba-c78be8170837.jpg&#34;/&#62;&#60;img src=&#34;https://oss.dinghuo123.com/product/detail/images/2548203/d08c4a76-7c67-4105-bbf7-f3e407143fe5.jpg&#34;/&#62;&#60;img src=&#34;https://oss.dinghuo123.com/product/detail/images/2548203/e0522c2b-026a-43ff-a1c6-9249c5c33b0b.jpg&#34;/&#62;&#60;img src=&#34;https://oss.dinghuo123.com/product/detail/images/2548203/504d71f5-9c53-40fc-af9c-6197a8e26fb8.jpg&#34;/&#62;&#60;img src=&#34;https://oss.dinghuo123.com/product/detail/images/2548203/53484cfe-1fbd-4a26-9563-d80be02b3f9b.jpg&#34;/&#62;&#60;img src=&#34;https://oss.dinghuo123.com/product/detail/images/2548203/dedb8b36-b73a-4c2b-9bf2-4ed39b052139.jpg&#34;/&#62;&#60;img src=&#34;https://oss.dinghuo123.com/product/detail/images/2548203/db36fca7-06bd-4a4e-b7e9-49698e2e962a.jpg&#34;/&#62;&#60;img src=&#34;https://oss.dinghuo123.com/product/detail/images/2548203/aa5bde55-28a9-40dd-9237-77adac7758d3.jpg&#34;/&#62;&#60;img src=&#34;https://oss.dinghuo123.com/product/detail/images/2548203/62523d57-d1ba-4731-bee4-6cd26b0f23d0.jpg&#34;/&#62;&#60;img src=&#34;https://oss.dinghuo123.com/product/detail/images/2548203/fa70fa01-6cb9-4c35-9bf8-f1c879cc1520.jpg&#34;/&#62;&#60;img src=&#34;https://oss.dinghuo123.com/product/detail/images/2548203/477a1dad-c0a4-4150-b2a0-13d8b407e6cb.jpg&#34;/&#62;&#60;img src=&#34;https://oss.dinghuo123.com/product/detail/images/2548203/a291c887-fe01-4ecc-aed2-51305c4a9b36.jpg&#34;/&#62;&#60;img src=&#34;https://oss.dinghuo123.com/product/detail/images/2548203/651b86a7-fec0-4329-a80a-6d70fd5630d1.jpg&#34;/&#62;&#60;img src=&#34;https://oss.dinghuo123.com/product/detail/images/2548203/bf8268a5-812a-4766-96c5-e66b3f1c67d6.jpg&#34;/&#62;&#60;img src=&#34;https://oss.dinghuo123.com/product/detail/images/2548203/f9308b89-2608-4382-b0b7-f6645d4c6374.jpg&#34;/&#62;&#60;img src=&#34;https://oss.dinghuo123.com/product/detail/images/2548203/fcfbb534-cfa3-4fdb-a71b-95ada856a5d0.jpg&#34;/&#62;&#60;img src=&#34;https://oss.dinghuo123.com/product/detail/images/2548203/740acaad-1bce-41fd-a7de-2b5bb1b0f1d3.jpg&#34;/&#62;&#60;img src=&#34;https://oss.dinghuo123.com/product/detail/images/2548203/31a7a67f-921a-4b49-b662-7d6a44ca653b.jpg&#34;/&#62;&#60;img src=&#34;https://oss.dinghuo123.com/product/detail/images/2548203/351b02c1-1ea7-4ddc-9045-c462391eeb07.jpg&#34;/&#62;&#60;img src=&#34;https://oss.dinghuo123.com/product/detail/images/2548203/319c5e73-4a0f-4443-8a9b-85c401730e8f.jpg&#34;/&#62;&#60;img src=&#34;https://oss.dinghuo123.com/product/detail/images/2548203/b9b99b70-0f0b-43f0-987f-e528499f048c.jpg&#34;/&#62;&#60;img src=&#34;https://oss.dinghuo123.com/product/detail/images/2548203/77afa47e-deb3-41d0-9fa0-5e080f67a824.jpg&#34;/&#62;&#60;img src=&#34;https://oss.dinghuo123.com/product/detail/images/2548203/d0f6f0c1-e970-4030-ba22-b1366525b57f.jpg&#34;/&#62;&#60;img src=&#34;https://oss.dinghuo123.com/product/detail/images/2548203/3277476d-f0f8-4ffe-8834-ab0014c38540.jpg&#34;/&#62;&#60;img src=&#34;https://oss.dinghuo123.com/product/detail/images/2548203/26f1ee06-f31c-4734-b4c2-6e5e3633d4bc.jpg&#34;/&#62;&#60;img src=&#34;https://oss.dinghuo123.com/product/detail/images/2548203/6d739c05-15e4-4a20-a3d6-ca6729da41f6.jpg&#34;/&#62;&#60;img src=&#34;https://oss.dinghuo123.com/product/detail/images/2548203/d2ce3853-e96f-432e-9612-a9c20933dcc4.jpg&#34;/&#62;&#60;img src=&#34;https://oss.dinghuo123.com/product/detail/images/2548203/97c431ed-a3b2-4fdf-a7f9-4443b191679e.jpg&#34;/&#62;&#60;img src=&#34;https://oss.dinghuo123.com/product/detail/images/2548203/da66c626-8a08-408a-9c68-1141861fb07d.jpg&#34;/&#62;&#60;img src=&#34;https://oss.dinghuo123.com/product/detail/images/2548203/6a66d40e-ab7e-4f56-8127-7a58e2c0a73d.jpg&#34;/&#62;&#60;img src=&#34;https://oss.dinghuo123.com/product/detail/images/2548203/33de020c-ec49-4cdf-9549-a84cd3967719.jpg&#34;/&#62;&#60;img src=&#34;https://oss.dinghuo123.com/product/detail/images/2548203/0ba8796c-4167-469e-b603-22ff650c9736.jpg&#34;/&#62;&#60;img src=&#34;https://oss.dinghuo123.com/product/detail/images/2548203/d5c1e821-b4bb-4c07-9bb6-7c36414d116f.jpg&#34;/&#62;&#60;/p&#62;",
    "queryInventoryStatus": [],
    "remark": "",
    "isCart": false,
    "delete": "0",
    "priceList": [
      {
        "marketPrice": 208,
        "product": null,
        "productId": 717012097,
        "maxQuantity": 0,
        "productSummaryId": 717012096,
        "remark": "",
        "unitPrices": [
          {
            "unitId": 6872734,
            "orderPrice": 70
          }
        ],
        "customerTypeId": 4331189,
        "customerType": null,
        "modifyTime": {
          "date": 10,
          "hours": 15,
          "seconds": 46,
          "month": 11,
          "timezoneOffset": -480,
          "year": 125,
          "minutes": 15,
          "time": 1765350946000,
          "day": 3
        },
        "isForbidden": "0",
        "minQuantity": 0,
        "unitListPrice": [],
        "dbid": 2548203,
        "orderPrice": 70,
        "id": 4415561395,
        "status": ""
      }
    ],
    "productUnitId": 6872734,
    "subProductList": [],
    "priceListType": [
      {
        "marketPrice": 208,
        "product": null,
        "productId": 717012097,
        "maxQuantity": 0,
        "productSummaryId": 717012096,
        "remark": "",
        "unitPrices": [
          {
            "unitId": 6872734,
            "orderPrice": 70
          }
        ],
        "customerTypeId": 4331189,
        "customerType": null,
        "modifyTime": {
          "date": 10,
          "hours": 15,
          "seconds": 46,
          "month": 11,
          "timezoneOffset": -480,
          "year": 125,
          "minutes": 15,
          "time": 1765350946000,
          "day": 3
        },
        "isForbidden": "0",
        "minQuantity": 0,
        "unitListPrice": [],
        "dbid": 2548203,
        "orderPrice": 70,
        "id": 4415561395,
        "status": ""
      }
    ],
    "customerTypeId": 0,
    "attachmentList": [],
    "productAuxUnit": null,
    "c_extra": {},
    "prepareCount": 0,
    "orderPrice": 208,
    "imgUrl_cut": "2548203/215733a4-cadf-4e8f-be1a-64225e374939.jpg@0-0-1280-1280a.jpg",
    "returnCart": null,
    "productType": {
      "mainImg": null,
      "parentTypeId": 0,
      "src": "",
      "typeLevel": 1,
      "imgUrl_200": "",
      "leafTypeFlag": "1",
      "subTypeTotalNum": 0,
      "advanceCutSize": "",
      "isDefault": "",
      "modifyTime": null,
      "showPageType": 1,
      "dbid": 2548203,
      "mainImgUrl": "",
      "name": "益肤-D",
      "id": 20997477,
      "subTypeList": [],
      "status": "0"
    },
    "productTagModelList": [],
    "mulspec2Value": "",
    "pullNewCommissionRuleVO": null,
    "mulspec5Value": "",
    "album": [
      "2548203/65db3fcf-c1a5-41cc-93c4-29356feaddc4.png",
      "2548203/f59a9983-2d40-49b8-adb2-b18fdd1393e3.png",
      "2548203/478173a6-2862-406c-bb63-0090f33e4cc4.jpg",
      "2548203/907bb63d-c3d1-459d-a031-8522b62f8db7.jpg",
      "2548203/c845f20a-0e79-4b9c-aeef-710acbe6492c.jpg"
    ],
    "multiUnitTemp": "",
    "tagIdsLike": [],
    "property9": "",
    "imgUrl_480": "2548203/215733a4-cadf-4e8f-be1a-64225e374939.jpg@0-0-1280-1280a_480w_480h.jpg",
    "packageSpec3Name": "",
    "property6": "",
    "mulspec4Name": "",
    "property5": "",
    "productTypeId": 20997477,
    "property8": "",
    "property7": "",
    "imgUrl": "2548203/215733a4-cadf-4e8f-be1a-64225e374939.jpg@0-0-1280-1280a.jpg",
    "salesProducts": [],
    "opTime": {
      "date": 29,
      "hours": 10,
      "seconds": 2,
      "month": 11,
      "timezoneOffset": -480,
      "year": 125,
      "minutes": 29,
      "time": 1766975342000,
      "day": 1
    },
    "summaryCount": 0
  }
]