[
  {
    "isCombination": false,
    "minPromotionOrderPrice": 0,
    "productVideoId": 0,
    "originOrderCount": 0,
    "productBrand": {
      "modifyTime": null,
      "dbid": 2548203,
      "name": "蕉下",
      "id": 18791200,
      "status": 0
    },
    "mulspec3Value": "",
    "minPromotionOrderRate": 0,
    "promotionStatus": "",
    "property2": "",
    "property1": "",
    "property4": "",
    "property3": "",
    "queryProductTypeIds": [],
    "queryStatus": [],
    "valueSpecDesc": "",
    "inventories": [],
    "inventoryModifyTime": {
      "date": 31,
      "hours": 12,
      "seconds": 29,
      "month": 11,
      "timezoneOffset": -480,
      "year": 125,
      "minutes": 11,
      "time": 1767154289000,
      "day": 3
    },
    "productVideoModel": null,
    "beginTime": "",
    "id": 981697277,
    "mulspecList": null,
    "mainUnitId": 0,
    "mulspec3Name": "",
    "costPriceSql": 0,
    "specDesc": "",
    "mainPrice": 0,
    "inventoryStatus": "",
    "queryProductInventoryStatus": [],
    "productBrandId": 18791200,
    "showTypeIds": [],
    "version": 0,
    "packagespecStatus": "0",
    "isScekillProduct": "",
    "mainUnitName": "",
    "outModifyTime": "",
    "isForbidden": "",
    "imgUrl_60": "2548203/9e58eacf-7c51-4d45-9b76-96e834b7150b.jpg@0-0-800-800a_60w_60h.jpg",
    "mulspec1Value": "",
    "mulspec4Value": "",
    "dbid": 2548203,
    "inventoryVersion": 32,
    "onWayCount": 0,
    "mulspec1Name": "",
    "status": "0",
    "marketPrice": 199,
    "productSummaryId": 981697276,
    "inventoryUpWarn": -1,
    "modifyEndTime": "",
    "packageSpec3Value": "",
    "orderPriceSql": 199,
    "marketPriceSql": 199,
    "shoppingCart": {},
    "queryProductIds": [],
    "sortNum": 10,
    "existImage": false,
    "productCombinationContents": [],
    "productSpec": "",
    "syncProduct": false,
    "costPrice": 0,
    "inventoryCount": 17,
    "mulspecTemplateName": "",
    "imgUrl_200": "2548203/9e58eacf-7c51-4d45-9b76-96e834b7150b.jpg@0-0-800-800a_200w_200h.jpg",
    "multipleProductTypeModel": null,
    "exactBarcode": "",
    "promotionProductIds": [],
    "packageSpec2Name": "",
    "createTime": {
      "date": 17,
      "hours": 14,
      "seconds": 34,
      "month": 5,
      "timezoneOffset": -480,
      "year": 125,
      "minutes": 10,
      "time": 1750140634000,
      "day": 2
    },
    "productUnitName": "顶",
    "purchaseScore": 0,
    "albumList": [
      {
        "productId": 981697277,
        "productSummaryId": 981697276,
        "imgUrl_480": "2548203/95e7a00b-5275-457c-82d9-8fb456404a2a.jpg@480w_480h.jpg",
        "remark": "",
        "imgUrl_200": "2548203/95e7a00b-5275-457c-82d9-8fb456404a2a.jpg@200w_200h.jpg",
        "type": 1,
        "imgName": "主1 (4).jpg",
        "imgUrl": "95e7a00b-5275-457c-82d9-8fb456404a2a.jpg",
        "advanceCutSize": "",
        "proposeFormat": ".jpg",
        "size": 76904,
        "createTime": {
          "date": 18,
          "hours": 10,
          "seconds": 57,
          "month": 5,
          "timezoneOffset": -480,
          "year": 125,
          "minutes": 2,
          "time": 1750212177000,
          "day": 3
        },
        "imgUrl_60": "2548203/95e7a00b-5275-457c-82d9-8fb456404a2a.jpg@60w_60h.jpg",
        "dbid": 2548203,
        "sortNum": 0,
        "id": 132360060,
        "imgUrl_cut": "2548203/95e7a00b-5275-457c-82d9-8fb456404a2a.jpg",
        "imgVersion": 1000
      },
      {
        "productId": 981697277,
        "productSummaryId": 981697276,
        "imgUrl_480": "2548203/48ec7341-737c-4137-bc3f-eadee7c34357.jpg@480w_480h.jpg",
        "remark": "",
        "imgUrl_200": "2548203/48ec7341-737c-4137-bc3f-eadee7c34357.jpg@200w_200h.jpg",
        "type": 1,
        "imgName": "主1 (1).jpg",
        "imgUrl": "48ec7341-737c-4137-bc3f-eadee7c34357.jpg",
        "advanceCutSize": "",
        "proposeFormat": ".jpg",
        "size": 79636,
        "createTime": {
          "date": 18,
          "hours": 10,
          "seconds": 57,
          "month": 5,
          "timezoneOffset": -480,
          "year": 125,
          "minutes": 2,
          "time": 1750212177000,
          "day": 3
        },
        "imgUrl_60": "2548203/48ec7341-737c-4137-bc3f-eadee7c34357.jpg@60w_60h.jpg",
        "dbid": 2548203,
        "sortNum": 1,
        "id": 132360061,
        "imgUrl_cut": "2548203/48ec7341-737c-4137-bc3f-eadee7c34357.jpg",
        "imgVersion": 1000
      },
      {
        "productId": 981697277,
        "productSummaryId": 981697276,
        "imgUrl_480": "2548203/765b098f-6887-462d-b466-03a33f5a9e08.jpg@480w_480h.jpg",
        "remark": "",
        "imgUrl_200": "2548203/765b098f-6887-462d-b466-03a33f5a9e08.jpg@200w_200h.jpg",
        "type": 1,
        "imgName": "主1 (2).jpg",
        "imgUrl": "765b098f-6887-462d-b466-03a33f5a9e08.jpg",
        "advanceCutSize": "",
        "proposeFormat": ".jpg",
        "size": 69945,
        "createTime": {
          "date": 18,
          "hours": 10,
          "seconds": 57,
          "month": 5,
          "timezoneOffset": -480,
          "year": 125,
          "minutes": 2,
          "time": 1750212177000,
          "day": 3
        },
        "imgUrl_60": "2548203/765b098f-6887-462d-b466-03a33f5a9e08.jpg@60w_60h.jpg",
        "dbid": 2548203,
        "sortNum": 2,
        "id": 132360062,
        "imgUrl_cut": "2548203/765b098f-6887-462d-b466-03a33f5a9e08.jpg",
        "imgVersion": 1000
      },
      {
        "productId": 981697277,
        "productSummaryId": 981697276,
        "imgUrl_480": "2548203/493dad4f-beed-465a-9ae0-2527a019300d.jpg@480w_480h.jpg",
        "remark": "",
        "imgUrl_200": "2548203/493dad4f-beed-465a-9ae0-2527a019300d.jpg@200w_200h.jpg",
        "type": 1,
        "imgName": "主1 (3).jpg",
        "imgUrl": "493dad4f-beed-465a-9ae0-2527a019300d.jpg",
        "advanceCutSize": "",
        "proposeFormat": ".jpg",
        "size": 103618,
        "createTime": {
          "date": 18,
          "hours": 10,
          "seconds": 57,
          "month": 5,
          "timezoneOffset": -480,
          "year": 125,
          "minutes": 2,
          "time": 1750212177000,
          "day": 3
        },
        "imgUrl_60": "2548203/493dad4f-beed-465a-9ae0-2527a019300d.jpg@60w_60h.jpg",
        "dbid": 2548203,
        "sortNum": 3,
        "id": 132360063,
        "imgUrl_cut": "2548203/493dad4f-beed-465a-9ae0-2527a019300d.jpg",
        "imgVersion": 1000
      }
    ],
    "property10": "",
    "mulspec5Name": "",
    "endTime": "",
    "mulspecTemplateId": 0,
    "comboFlag": false,
    "keywords": "",
    "packageSpec1Value": "",
    "sortTime": {
      "date": 18,
      "hours": 11,
      "seconds": 19,
      "month": 7,
      "timezoneOffset": -480,
      "year": 125,
      "minutes": 8,
      "time": 1755486499000,
      "day": 1
    },
    "modifyBeginTime": "",
    "promotionStrategyList": [],
    "spec": "",
    "modifyTime": {
      "date": 31,
      "hours": 12,
      "seconds": 29,
      "month": 11,
      "timezoneOffset": -480,
      "year": 125,
      "minutes": 11,
      "time": 1767154289000,
      "day": 3
    },
    "packageSpec2Value": "",
    "shoppingCartProductType": 0,
    "productTypeName": "",
    "queryProductBrandIds": [],
    "warningCount": -1,
    "surplusCostMoney": 0,
    "barcode": "",
    "productCollection": {},
    "priceCustomerList": [],
    "weight": 0,
    "mainCount": 0,
    "promotionStrategy": {},
    "mulspec2Name": "",
    "inventoryCountisForbid": 0,
    "name": "蕉下零触全防护空顶防晒帽AS721（暮灰紫）（非质量问题不退换）",
    "desimgList": [],
    "isGroup": "0",
    "productOrderMultiple": 0,
    "dataSource": "",
    "queryBarcode": "",
    "packageSpec1Name": "",
    "mainImg": {
      "productId": 981697277,
      "productSummaryId": 981697276,
      "imgUrl_480": "2548203/9e58eacf-7c51-4d45-9b76-96e834b7150b.jpg@0-0-800-800a_480w_480h.jpg",
      "remark": "",
      "imgUrl_200": "2548203/9e58eacf-7c51-4d45-9b76-96e834b7150b.jpg@0-0-800-800a_200w_200h.jpg",
      "type": 0,
      "imgName": "主.jpg",
      "imgUrl": "9e58eacf-7c51-4d45-9b76-96e834b7150b.jpg",
      "advanceCutSize": "0-0-800-800",
      "proposeFormat": ".jpg",
      "size": 55342,
      "createTime": {
        "date": 18,
        "hours": 10,
        "seconds": 57,
        "month": 5,
        "timezoneOffset": -480,
        "year": 125,
        "minutes": 2,
        "time": 1750212177000,
        "day": 3
      },
      "imgUrl_60": "2548203/9e58eacf-7c51-4d45-9b76-96e834b7150b.jpg@0-0-800-800a_60w_60h.jpg",
      "dbid": 2548203,
      "sortNum": 0,
      "id": 132360059,
      "imgUrl_cut": "2548203/9e58eacf-7c51-4d45-9b76-96e834b7150b.jpg@0-0-800-800a.jpg",
      "imgVersion": 1000
    },
    "code": "P2025061615",
    "supplierId": 0,
    "priceListCustomer": [],
    "productSummaryIds": [],
    "customAttributeStitch": "",
    "tagIds": [
      3,
      3132310
    ],
    "unitList": [
      {
        "marketPrice": 199,
        "unitName": "顶",
        "forbidden": "0",
        "productSummaryId": 981697276,
        "costPrice": 0,
        "version": 0,
        "returnOrderPrice": 0,
        "modifyTime": null,
        "createTime": null,
        "rate": 1,
        "dbid": 2548203,
        "unitId": 46287967,
        "orderPrice": 199,
        "id": 41597973,
        "barcode": ""
      }
    ],
    "description": "&#60;p&#62;&#60;span style=&#34;text-wrap-mode: wrap;&#34;&#62;商品介绍&#60;/span&#62;&#60;/p&#62;&#60;p&#62;&#60;span style=&#34;text-wrap-mode: wrap;&#34;&#62;&#60;img src=&#34;https://oss.dinghuo123.com/product/detail/images/2548203/24bd477e-8ede-4194-b072-8f1c1997ebf7.jpg&#34;/&#62;&#60;img src=&#34;https://oss.dinghuo123.com/product/detail/images/2548203/1f4c19a5-905a-404c-9fd2-dc08e2f88d3f.jpg&#34;/&#62;&#60;img src=&#34;https://oss.dinghuo123.com/product/detail/images/2548203/a6e2e179-addb-4440-adae-0f3915d9f831.jpg&#34;/&#62;&#60;img src=&#34;https://oss.dinghuo123.com/product/detail/images/2548203/43260882-7102-4c60-bab9-14f8ec4eb332.jpg&#34;/&#62;&#60;img src=&#34;https://oss.dinghuo123.com/product/detail/images/2548203/52292a8f-f041-45b0-b31d-b189cbf77cbb.jpg&#34;/&#62;&#60;img src=&#34;https://oss.dinghuo123.com/product/detail/images/2548203/815a5398-0289-4085-a34f-91e301306669.jpg&#34;/&#62;&#60;img src=&#34;https://oss.dinghuo123.com/product/detail/images/2548203/64dcda72-7e13-4933-8806-9be6ebe62eaf.jpg&#34;/&#62;&#60;img src=&#34;https://oss.dinghuo123.com/product/detail/images/2548203/34a47020-5b98-493c-89be-fe64843a6cc3.jpg&#34;/&#62;&#60;img src=&#34;https://oss.dinghuo123.com/product/detail/images/2548203/04cab418-1116-4043-89a5-68091f7c16a2.jpg&#34;/&#62;&#60;img src=&#34;https://oss.dinghuo123.com/product/detail/images/2548203/3102274d-5b02-4bef-a27c-1de2d64bd742.jpg&#34;/&#62;&#60;img src=&#34;https://oss.dinghuo123.com/product/detail/images/2548203/4b122edd-c8ef-4a59-a57a-bcb2c1d7d1e1.jpg&#34;/&#62;&#60;img src=&#34;https://oss.dinghuo123.com/product/detail/images/2548203/34d17ee9-5c48-47a1-abcc-b251ce493cdd.jpg&#34;/&#62;&#60;img src=&#34;https://oss.dinghuo123.com/product/detail/images/2548203/2467bfdf-9db0-4a9f-b9d4-9017c56f1d65.jpg&#34;/&#62;&#60;img src=&#34;https://oss.dinghuo123.com/product/detail/images/2548203/9e0e4efe-5c6c-4ee9-baf9-e0992e78aa87.jpg&#34;/&#62;&#60;img src=&#34;https://oss.dinghuo123.com/product/detail/images/2548203/5cacef91-a9a1-44bc-ab38-74dfe72903d9.jpg&#34;/&#62;&#60;img src=&#34;https://oss.dinghuo123.com/product/detail/images/2548203/9104a9ec-e490-48ea-a684-e949add364ac.jpg&#34;/&#62;&#60;img src=&#34;https://oss.dinghuo123.com/product/detail/images/2548203/4bde0602-aedd-4da7-a8bf-4c7f462b6845.jpg&#34;/&#62;&#60;img src=&#34;https://oss.dinghuo123.com/product/detail/images/2548203/326d5ada-6709-4afe-a4ee-5a80a0adc02e.jpg&#34;/&#62;&#60;img src=&#34;https://oss.dinghuo123.com/product/detail/images/2548203/28e3c479-5d7e-4010-b40e-43962ccc7850.jpg&#34;/&#62;&#60;img src=&#34;https://oss.dinghuo123.com/product/detail/images/2548203/85a62a94-c9f9-4af3-981f-bb16b4b7d738.jpg&#34;/&#62;&#60;img src=&#34;https://oss.dinghuo123.com/product/detail/images/2548203/9f5463f8-0d7f-4cfd-81ae-5a97fd08232e.jpg&#34;/&#62;&#60;img src=&#34;https://oss.dinghuo123.com/product/detail/images/2548203/40b25b1f-0582-4f2f-bb2e-4c35aa7e7359.jpg&#34;/&#62;&#60;img src=&#34;https://oss.dinghuo123.com/product/detail/images/2548203/e67c5182-bffe-4bb1-8166-4de5bcabc241.jpg&#34;/&#62;&#60;img src=&#34;https://oss.dinghuo123.com/product/detail/images/2548203/2a0ff699-74b2-4db8-a591-2e51e5b18c0c.jpg&#34;/&#62;&#60;img src=&#34;https://oss.dinghuo123.com/product/detail/images/2548203/229adef5-852e-43f6-ba21-7766a58e8b7d.jpg&#34;/&#62;&#60;img src=&#34;https://oss.dinghuo123.com/product/detail/images/2548203/1efb2505-ffe7-426a-80ee-6e7d3788f2d7.jpg&#34;/&#62;&#60;img src=&#34;https://oss.dinghuo123.com/product/detail/images/2548203/cae34dce-4c2e-4f63-bb62-073fb53c55bf.jpg&#34;/&#62;&#60;img src=&#34;https://oss.dinghuo123.com/product/detail/images/2548203/6a8b6fbb-1179-4058-8832-d524ba38acd8.jpg&#34;/&#62;&#60;img src=&#34;https://oss.dinghuo123.com/product/detail/images/2548203/5e00ccf4-b5af-434d-858d-a2724caaeb45.jpg&#34;/&#62;&#60;img src=&#34;https://oss.dinghuo123.com/product/detail/images/2548203/84c73469-7dfb-4681-921c-524422d4b68e.jpg&#34;/&#62;&#60;img src=&#34;https://oss.dinghuo123.com/product/detail/images/2548203/0d223012-6422-4691-a4af-9223f2810191.jpg&#34;/&#62;&#60;img src=&#34;https://oss.dinghuo123.com/product/detail/images/2548203/76c30cfa-bf7a-4e59-b9f1-187f3ff6b7ee.jpg&#34;/&#62;&#60;img src=&#34;https://oss.dinghuo123.com/product/detail/images/2548203/4aced567-3bd9-41f3-b4a6-9d5fa4e9d576.jpg&#34;/&#62;&#60;img src=&#34;https://oss.dinghuo123.com/product/detail/images/2548203/f760e075-7f2f-42ef-ba22-5fca55b6db1c.jpg&#34;/&#62;&#60;/span&#62;&#60;/p&#62;",
    "queryInventoryStatus": [],
    "remark": "",
    "isCart": false,
    "delete": "0",
    "priceList": [
      {
        "marketPrice": 0,
        "product": null,
        "productId": 981697277,
        "maxQuantity": 0,
        "productSummaryId": 981697276,
        "remark": "",
        "unitPrices": [
          {
            "unitId": 46287967,
            "orderPrice": 115
          }
        ],
        "customerTypeId": 4331189,
        "customerType": null,
        "modifyTime": {
          "date": 11,
          "hours": 17,
          "seconds": 11,
          "month": 6,
          "timezoneOffset": -480,
          "year": 125,
          "minutes": 30,
          "time": 1752226211000,
          "day": 5
        },
        "isForbidden": "0",
        "minQuantity": 0,
        "unitListPrice": [],
        "dbid": 2548203,
        "orderPrice": 115,
        "id": 7566786750,
        "status": ""
      }
    ],
    "productUnitId": 46287967,
    "subProductList": [],
    "priceListType": [
      {
        "marketPrice": 0,
        "product": null,
        "productId": 981697277,
        "maxQuantity": 0,
        "productSummaryId": 981697276,
        "remark": "",
        "unitPrices": [
          {
            "unitId": 46287967,
            "orderPrice": 115
          }
        ],
        "customerTypeId": 4331189,
        "customerType": null,
        "modifyTime": {
          "date": 11,
          "hours": 17,
          "seconds": 11,
          "month": 6,
          "timezoneOffset": -480,
          "year": 125,
          "minutes": 30,
          "time": 1752226211000,
          "day": 5
        },
        "isForbidden": "0",
        "minQuantity": 0,
        "unitListPrice": [],
        "dbid": 2548203,
        "orderPrice": 115,
        "id": 7566786750,
        "status": ""
      }
    ],
    "customerTypeId": 0,
    "attachmentList": [],
    "productAuxUnit": null,
    "c_extra": {},
    "prepareCount": 0,
    "orderPrice": 199,
    "imgUrl_cut": "2548203/9e58eacf-7c51-4d45-9b76-96e834b7150b.jpg@0-0-800-800a.jpg",
    "returnCart": null,
    "productType": {
      "mainImg": null,
      "parentTypeId": 0,
      "src": "",
      "typeLevel": 1,
      "imgUrl_200": "",
      "leafTypeFlag": "1",
      "subTypeTotalNum": 0,
      "advanceCutSize": "",
      "isDefault": "",
      "modifyTime": null,
      "showPageType": 1,
      "dbid": 2548203,
      "mainImgUrl": "",
      "name": "蕉下-D",
      "id": 24356440,
      "subTypeList": [],
      "status": "0"
    },
    "productTagModelList": [],
    "mulspec2Value": "",
    "pullNewCommissionRuleVO": null,
    "mulspec5Value": "",
    "album": [
      "2548203/95e7a00b-5275-457c-82d9-8fb456404a2a.jpg",
      "2548203/48ec7341-737c-4137-bc3f-eadee7c34357.jpg",
      "2548203/765b098f-6887-462d-b466-03a33f5a9e08.jpg",
      "2548203/493dad4f-beed-465a-9ae0-2527a019300d.jpg"
    ],
    "multiUnitTemp": "",
    "tagIdsLike": [],
    "property9": "",
    "imgUrl_480": "2548203/9e58eacf-7c51-4d45-9b76-96e834b7150b.jpg@0-0-800-800a_480w_480h.jpg",
    "packageSpec3Name": "",
    "property6": "",
    "mulspec4Name": "",
    "property5": "",
    "productTypeId": 24356440,
    "property8": "",
    "property7": "",
    "imgUrl": "2548203/9e58eacf-7c51-4d45-9b76-96e834b7150b.jpg@0-0-800-800a.jpg",
    "salesProducts": [],
    "opTime": null,
    "summaryCount": 0
  }
]